{
  "total": 1,
  "offset": 0,
  "data": [
    {
      "paperId": "e97ac50fb96921b5d0f8efff838c3ee0348fc22e",
      "externalIds": {
        "DBLP": "conf/icml/LiangP15",
        "MAG": "1879053045",
        "CorpusId": 9165091
      },
      "url": "https://www.semanticscholar.org/paper/e97ac50fb96921b5d0f8efff838c3ee0348fc22e",
      "title": "Landmarking Manifolds with Gaussian Processes",
      "venue": "International Conference on Machine Learning",
      "year": 2015,
      "referenceCount": 27,
      "citationCount": 14,
      "authors": [
        {
          "authorId": "1702877",
          "name": "Dawen Liang"
        },
        {
          "authorId": "143855009",
          "name": "J. Paisley"
        }
      ]
    }
  ]
}